awp/__init__.py
awp/argparse_extras.py
awp/data/config-schema.json
awp/main.py
awp/packager.py
awp/validator.py
alfred_workflow_packager-3.2.1.dist-info/WHEEL
alfred_workflow_packager-3.2.1.dist-info/entry_points.txt
alfred_workflow_packager-3.2.1.dist-info/METADATA
alfred_workflow_packager-3.2.1.dist-info/RECORD
