Metadata-Version: 2.4
Name: alfred-workflow-packager
Version: 3.2.1
Summary: A CLI utility for packaging and exporting Alfred workflows
Keywords: alfred,workflow,package,export
Author: Caleb Evans
Author-email: Caleb Evans <caleb@calebevans.me>
License-Expression: MIT
Requires-Dist: jsonschema>=4,<5
Maintainer: Caleb Evans
Maintainer-email: Caleb Evans <caleb@calebevans.me>
Requires-Python: >=3.9
Project-URL: changelog, https://github.com/caleb531/alfred-workflow-packager/releases
Project-URL: documentation, https://github.com/caleb531/alfred-workflow-packager#readme
Project-URL: homepage, https://github.com/caleb531/alfred-workflow-packager
Project-URL: repository, https://github.com/caleb531/alfred-workflow-packager
